ukr/__init__.py
ukr/__main__.py
ukr/graph_utils.py
ukr/utils.py
ukr/wfst.py
ukr/data/__init__.py
ukr/data/measurements.tsv
ukr/data/month.tsv
ukr/data/suppletive.tsv
ukr/data/currency/currency_major.tsv
ukr/data/currency/currency_minor.tsv
ukr/data/numbers/__init__.py
ukr/data/numbers/cardinals_billion.tsv
ukr/data/numbers/cardinals_million.tsv
ukr/data/numbers/cardinals_thousand.tsv
ukr/data/numbers/decimal_delimiter.tsv
ukr/data/numbers/decimal_endings.tsv
ukr/data/numbers/quantity.tsv
ukr/data/numbers/cardinal/accusative/cardinals_digit.tsv
ukr/data/numbers/cardinal/accusative/cardinals_hundred.tsv
ukr/data/numbers/cardinal/accusative/cardinals_teen.tsv
ukr/data/numbers/cardinal/accusative/cardinals_ties.tsv
ukr/data/numbers/cardinal/accusative/cardinals_zero.tsv
ukr/data/numbers/cardinal/dative/cardinals_digit.tsv
ukr/data/numbers/cardinal/dative/cardinals_hundred.tsv
ukr/data/numbers/cardinal/dative/cardinals_teen.tsv
ukr/data/numbers/cardinal/dative/cardinals_ties.tsv
ukr/data/numbers/cardinal/dative/cardinals_zero.tsv
ukr/data/numbers/cardinal/genitive/cardinals_digit.tsv
ukr/data/numbers/cardinal/genitive/cardinals_hundred.tsv
ukr/data/numbers/cardinal/genitive/cardinals_teen.tsv
ukr/data/numbers/cardinal/genitive/cardinals_ties.tsv
ukr/data/numbers/cardinal/genitive/cardinals_zero.tsv
ukr/data/numbers/cardinal/instrumental/cardinals_digit.tsv
ukr/data/numbers/cardinal/instrumental/cardinals_hundred.tsv
ukr/data/numbers/cardinal/instrumental/cardinals_teen.tsv
ukr/data/numbers/cardinal/instrumental/cardinals_ties.tsv
ukr/data/numbers/cardinal/instrumental/cardinals_zero.tsv
ukr/data/numbers/cardinal/nominative/cardinals_digit.tsv
ukr/data/numbers/cardinal/nominative/cardinals_hundred.tsv
ukr/data/numbers/cardinal/nominative/cardinals_teen.tsv
ukr/data/numbers/cardinal/nominative/cardinals_ties.tsv
ukr/data/numbers/cardinal/nominative/cardinals_zero.tsv
ukr/data/numbers/cardinal/prepositional/cardinals_digit.tsv
ukr_itn-0.1.8.dist-info/LICENSE
ukr_itn-0.1.8.dist-info/METADATA
ukr_itn-0.1.8.dist-info/WHEEL
ukr_itn-0.1.8.dist-info/top_level.txt
ukr_itn-0.1.8.dist-info/RECORD
