Metadata-Version: 2.1
Name: ukr-itn
Version: 0.1.8
Summary: WFST for Ukrainian Inverse Text Normalization (ITN) based on NVIDIA NeMo and Pynini
Author-email: Vasyl Spachynskyi <vspachyn@gmail.com>
Project-URL: Homepage, https://github.com/lociko/ukraine_itn_wfst
Project-URL: Bug Tracker, https://github.com/lociko/ukraine_itn_wfst/issues
Classifier: Programming Language :: Python :: 3
Classifier: License :: OSI Approved :: MIT License
Classifier: Operating System :: OS Independent
Classifier: Natural Language :: Ukrainian
Requires-Python: >=3.7
License-File: LICENSE
